{
  "introduction": "This video is the first lecture in a database class. It aims to provide a basic understanding of databases for individuals without prior experience. The lecture covers several important concepts, including the problems associated with storing data in a list, the benefits of using a database, the concept of related tables, and the various components of a database system. It also discusses the purpose of a project manager and the difference between personal and enterprise-level database systems.",
  "sections": [
    {
      "title": "Section 1: Understanding Databases",
      "content": [
        "Explanation of the purpose of databases and their role in data management.",
        "Discussion on the different types of databases and their use cases.",
        "Introduction to the concept of data integrity and its importance in databases.",
        "Explanation of the role of a database management system (DBMS) in organizing and managing data."
      ],
      "topics": ["Databases and Data Management", "Types of Databases", "Data Integrity", "DBMS and Data Organization"]
    },
    {
      "title": "Section 2: Storing Data in a List",
      "content": [
        "Explanation of the problems associated with storing data in a list, such as data redundancy and inconsistencies.",
        "Introduction to the concept of related tables and their role in eliminating these problems.",
        "Discussion on the use of foreign keys to link related tables.",
        "Explanation of the importance of data normalization in maintaining data consistency."
      ],
      "topics": ["Problems with List Storage", "Related Tables and Foreign Keys", "Data Normalization", "Maintaining Data Consistency"]
    },
    {
      "title": "Section 3: Components of a Database System",
      "content": [
        "Introduction to the various components of a database system, such as the database schema, tables, and indexes.",
        "Explanation of the role of a query language in interacting with the database.",
        "Discussion on the use of stored procedures and triggers in database management.",
        "Introduction to the concept of database security and its importance in protecting data."
      ],
      "topics": ["Database Schema and Tables", "Indexes and Query Language", "Stored Procedures and Triggers", "Database Security"]
    },
    {
      "title": "Section 4: Project Management in Databases",
      "content": [
        "Explanation of the role of a project manager in database development and management.",
        "Discussion on the importance of tracking project progress and managing resources effectively.",
        "Introduction to the concept of agile database development and its benefits.",
        "Explanation of the use of project management tools and methodologies in database projects."
      ],
      "topics": ["Project Management in Databases", "Resource Management", "Agile Database Development", "Project Management Tools and Methodologies"]
    },
    {
      "title": "Section 5: Personal vs. Enterprise-Level Databases",
      "content": [
        "Explanation of the differences between personal and enterprise-level databases.",
        "Discussion on the features and capabilities of enterprise-level databases.",
        "Introduction to the concept of scalability and its importance in enterprise database management.",
        "Explanation of the role of a database administrator in managing enterprise-level databases."
      ],
      "topics": ["Personal vs. Enterprise-Level Databases", "Features and Capabilities of Enterprise Databases", "Scalability in Enterprise Database Management", "Database Administrator in Enterprise Database Management"]
    }
  ],
  "topics": ["Databases and Data Management", "Related Tables and Foreign Keys", "Data Normalization", "Maintaining Data Consistency", "Database Schema and Tables", "Indexes and Query Language", "Stored Procedures and Triggers", "Database Security", "Project Management in Databases", "Resource Management", "Agile Database Development", "Project Management Tools and Methodologies", "Personal vs. Enterprise-Level Databases", "Features and Capabilities of Enterprise Databases", "Scalability in Enterprise Database Management", "Database Administrator in Enterprise Database Management"],
  "generalTopics": [
    {
      "name": "Database Management Systems",
      "complexity": 0.61
    },
    {
      "name": "Data Integrity",
      "complexity": 0.53
    },
    {
      "name": "Project Management in Databases",
      "complexity": 0.59
    }
  ]
}