{
  "introduction": "This video provides an overview of neural networks and their applications in deep learning. It explains how neural networks process data, learn patterns, and make predictions. The video also highlights various applications of neural networks in different fields such as facial recognition, stock price forecasting, and music composition.",
  "sections": [
    {
      "title": "Section 1: Introduction to Neural Networks",
      "content": [
        "Explanation of the structure and components of neural networks.",
        "Discussion on the forward and back propagation processes.",
        "Presentation of the activation functions and their role in the network.",
        "Overview of the training process and its importance."
      ],
      "topics": ["Neural Network Structure", "Forward Propagation", "Back Propagation", "Activation Functions", "Training Process"]
    },
    {
      "title": "Section 2: Applications of Neural Networks",
      "content": [
        "Examples of neural networks in action, including facial recognition and stock price forecasting.",
        "Discussion on the accuracy and effectiveness of neural networks in these applications.",
        "Presentation of other applications, such as music composition and image recognition.",
        "Examination of the potential future applications of neural networks."
      ],
      "topics": ["Facial Recognition", "Stock Price Forecasting", "Music Composition", "Image Recognition", "Future Applications"]
    },
    {
      "title": "Section 3: The Human Brain and Neural Networks",
      "content": [
        "Exploration of the similarities between the human brain and neural networks.",
        "Discussion on the potential for neural networks to replicate human cognitive abilities.",
        "Presentation of ongoing research in this area.",
        "Examination of the ethical implications of such advancements."
      ],
      "topics": ["Human Brain and Neural Networks", "Replicating Human Cognitive Abilities", "Ongoing Research", "Ethical Implications"]
    },
    {
      "title": "Section 4: Challenges and Limitations of Neural Networks",
      "content": [
        "Examination of the current limitations of neural networks, such as their inability to handle complex contexts and their reliance on large amounts of data.",
        "Discussion on the challenges of training and optimizing neural networks.",
        "Presentation of ongoing research to address these limitations.",
        "Examination of the potential for neural networks to improve in the future."
      ],
      "topics": ["Limitations of Neural Networks", "Training and Optimization Challenges", "Ongoing Research", "Future Improvements"]
    },
    {
      "title": "Section 5: Conclusion and Future Directions",
      "content": [
        "Recap of the key points covered in the video.",
        "Discussion on the potential for neural networks to revolutionize various fields.",
        "Presentation of ongoing research and development in this area.",
        "Examination of the future directions for neural networks and deep learning."
      ],
      "topics": ["Key Points Recap", "Potential for Revolution", "Ongoing Research and Development", "Future Directions"]
    }
  ],
  "topics": ["Neural Networks", "Deep Learning", "Applications", "Human Brain", "Limitations", "Future Directions"],
  "generalTopics": [
    {
      "name": "Artificial Intelligence and Machine Learning",
      "complexity": 0.65
    },
    {
      "name": "Computer Architecture",
      "complexity": 0.48
    },
    {
      "name": "Database Systems and Management",
      "complexity": 0.35
    }
  ]
}