{
  "introduction": "This video provides an overview of containers and their significance in software development. Containers are isolated environments that can be created quickly and easily, allowing developers to use different software and dependencies without affecting their local machine. The video covers the basics of containers, their creation using a container platform, and their deployment on various cloud platforms. It also discusses the benefits of using containers, such as flexibility, scalability, and ease of use.",
  "sections": [
    {
      "title": "Section 1: Introduction to Containers",
      "content": [
        "Explanation of containers and their purpose in software development.",
        "Comparison of containers to virtual machines and native applications.",
        "Overview of container platforms and their role in container creation.",
        "Discussion of the benefits of using containers."
      ],
      "topics": ["Containers", "Virtual Machines", "Native Applications", "Container Platforms", "Benefits"]
    },
    {
      "title": "Section 2: Creating Containers",
      "content": [
        "Explanation of the container image formation process using a Dockerfile.",
        "Description of the Dockerfile's role in adding changes to the final image.",
        "Discussion of the use of base images and premade images in container creation.",
        "Explanation of the importance of container communication and networking."
      ],
      "topics": ["Container Image Formation", "Dockerfile", "Base Images", "Premade Images", "Communication and Networking"]
    },
    {
      "title": "Section 3: Deploying Containers",
      "content": [
        "Overview of cloud platforms and their support for container deployment.",
        "Description of the process of deploying containers on a cloud platform.",
        "Explanation of the use of container registries for image storage and management.",
        "Discussion of the benefits of using container deployment on cloud platforms."
      ],
      "topics": ["Cloud Platforms", "Container Deployment Process", "Container Registries", "Benefits"]
    },
    {
      "title": "Section 4: Advanced Container Concepts",
      "content": [
        "Introduction to Kubernetes and its role in container orchestration.",
        "Explanation of the declarative deployment model used by Kubernetes.",
        "Discussion of the benefits of using Kubernetes for container management.",
        "Overview of other advanced container concepts, such as container swarming and service meshes."
      ],
      "topics": ["Kubernetes", "Declarative Deployment Model", "Container Management", "Advanced Concepts"]
    },
    {
      "title": "Section 5: Container Security and Best Practices",
      "content": [
        "Discussion of container security concerns and best practices.",
        "Explanation of the importance of container image scanning and vulnerability management.",
        "Overview of container networking security and isolation.",
        "Recommendations for container deployment and management security."
      ],
      "topics": ["Container Security", "Image Scanning", "Vulnerability Management", "Networking Security", "Deployment and Management Security"]
    }
  ],
  "topics": ["Containers", "Virtual Machines", "Native Applications", "Container Platforms", "Cloud Platforms", "Kubernetes", "Container Security", "Image Scanning", "Vulnerability Management", "Networking Security", "Deployment and Management Security"],
  "general topics": [
    {
      "name": "Algorithms and Data Structures",
      "complexity": "0.50"
    },
    {
      "name": "Artificial Intelligence (AI) and Machine Learning",
      "complexity": "0.70"
    },
    {
      "name": "Database Systems and Management",
      "complexity": "0.40"
    }
  ]
}