{
  "introduction": "In this video, Mike Plogger and Visme discuss data visualization and its importance in presenting information in a more accessible and understandable way. They cover various types of data visualizations, including line charts, pyramid charts, stacked area charts, radar charts, comparison infographics, and animated charts. They also provide design tips for creating effective data visualizations.",
  "sections": [
    {
      "title": "Section 1: Introduction to Data Visualization",
      "content": [
        "Data visualization is a graphical representation of data to make it easier to understand.",
        "Visualizations can help discover patterns, trends, and relationships in data.",
        "Visualizations can help present information in a more engaging and memorable way.",
        "Examples of data visualizations include line charts, pyramid charts, and comparison infographics."
      ],
      "topics": ["Data Visualization Definition", "Discovering Patterns and Trends", "Presenting Information Engagingly", "Examples of Data Visualizations"]
    },
    {
      "title": "Section 2: Types of Data Visualizations",
      "content": [
        "Line charts are useful for displaying change over time.",
        "Pyramid charts show the hierarchy of data, such as income or importance.",
        "Stacked area charts are similar to line charts but show change along the timeline.",
        "Radar charts are useful for comparing multiple variables at once."
      ],
      "topics": ["Line Charts", "Pyramid Charts", "Stacked Area Charts", "Radar Charts"]
    },
    {
      "title": "Section 3: Design Tips for Effective Data Visualizations",
      "content": [
        "Keep the design simple and organized.",
        "Use a limited number of colors and fonts.",
        "Include a legend to help viewers understand the data.",
        "Consider the context and audience when creating visualizations."
      ],
      "topics": ["Design Simplicity", "Font and Color Selection", "Legend Inclusion", "Audience Consideration"]
    },
    {
      "title": "Section 4: Using Data Visualization for Decision Making",
      "content": [
        "Data visualizations can help make informed decisions by presenting information in a clear and concise way.",
        "Visualizations can help identify trends and patterns that may not be immediately apparent.",
        "Visualizations can help compare different data sets and make side-by-side comparisons.",
        "Visualizations can help identify outliers and anomalies in the data."
      ],
      "topics": ["Informed Decision Making", "Identifying Trends and Patterns", "Side-by-Side Comparisons", "Outlier and Anomaly Detection"]
    },
    {
      "title": "Section 5: Creating Data Visualizations with Visme",
      "content": [
        "Visme is an online tool for creating data visualizations.",
        "Visme offers a variety of templates and customization options.",
        "Visme allows users to input their own data and create custom visualizations.",
        "Visme offers a user-friendly interface and a wide range of features."
      ],
      "topics": ["Visme Overview", "Template Customization", "Data Input and Customization", "User-Friendly Interface"]
    }
  ],
  "topics": ["Data Visualization Definition", "Discovering Patterns and Trends", "Presenting Information Engagingly", "Examples of Data Visualizations", "Design Simplicity", "Font and Color Selection", "Legend Inclusion", "Audience Consideration", "Informed Decision Making", "Identifying Trends and Patterns", "Side-by-Side Comparisons", "Outlier and Anomaly Detection", "Visme Overview", "Template Customization", "Data Input and Customization", "User-Friendly Interface"],
  "generalTopics": [
    {
      "name": "Data Science and Analytics",
      "complexity": 0.61
    },
    {
      "name": "Web Development and Internet Technologies",
      "complexity": 0.60
    },
    {
      "name": "Database Systems and Management",
      "complexity": 0.58
    }
  ]
}