{
  "introduction": "In this video, Harlan Harris discusses software architecture and choices, focusing on the high-level structure of a software system and the processes around it. He also talks about the importance of choosing the right technologies and boundaries for a project, considering factors such as the number of users and the performance of different algorithms. The video covers examples of architecture in production and the content stored in the database. Harlan also talks about testing and decision-making processes for choosing technologies and boundaries.",
  "sections": [
    {
      "title": "Section 1: Software Architecture and Choices",
      "content": [
        "Explanation of software architecture as the high-level structure of a software system.",
        "Discussion of choices, including technologies, boundaries, and user numbers.",
        "Examples of architecture in production.",
        "Introduction to the content stored in the database."
      ],
      "topics": ["Software Architecture", "Choices", "Examples in Production", "Database Content"]
    },
    {
      "title": "Section 2: Algorithms and Performance",
      "content": [
        "Explanation of algorithms and their performance.",
        "Discussion of latency and different types of algorithms.",
        "Quote from Russell Belkin about understanding performance evaluation.",
        "Examples of algorithms and their performance in real-world scenarios."
      ],
      "topics": ["Algorithms", "Performance", "Evaluation Tools", "Real-World Examples"]
    },
    {
      "title": "Section 3: Testing and Decision-Making",
      "content": [
        "Explanation of testing and decision-making processes.",
        "Discussion of different types of tests, including historical data and recent examples.",
        "Process for data flow testing and QA staff collaboration.",
        "Recent decision-making process for choosing technologies and boundaries."
      ],
      "topics": ["Testing", "Decision-Making", "Data Flow Testing", "Technology Choices"]
    },
    {
      "title": "Section 4: Database Systems and Management",
      "content": [
        "Explanation of database systems and management.",
        "Discussion of content stored in the database, including foreign keys and timestamps.",
        "Examples of database systems and their use cases.",
        "Impact of database systems on performance and scalability."
      ],
      "topics": ["Database Systems", "Content Storage", "Foreign Keys", "Timestamps", "Performance", "Scalability"]
    },
    {
      "title": "Section 5: Human-Computer Interaction and Programming Languages",
      "content": [
        "Explanation of human-computer interaction and programming languages.",
        "Discussion of user-facing applications and their importance.",
        "Examples of programming languages and their use cases.",
        "Impact of programming languages on user experience and scalability."
      ],
      "topics": ["Human-Computer Interaction", "Programming Languages", "User-Facing Applications", "Scalability"]
    }
  ],
  "topics": [
    "Software Architecture",
    "Algorithms and Performance",
    "Testing and Decision-Making",
    "Database Systems and Management",
    "Human-Computer Interaction and Programming Languages"
  ],
  "generalTopics": [
    {
      "name": "Software Engineering and System Design",
      "complexity": 0.61
    },
    {
      "name": "Data Science and Analytics",
      "complexity": 0.61
    },
    {
      "name": "Database Systems and Management",
      "complexity": 0.61
    }
  ]
}